wagtailspeech/__init__.py
wagtailspeech/admin.py
wagtailspeech/models.py
wagtailspeech/urls.py
wagtailspeech/utils.py
wagtailspeech/views.py
wagtailspeech/wagtail_hooks.py
wagtailspeech/migrations/0001_initial.py
wagtailspeech/migrations/__init__.py
wagtail_speech-0.2.0.dist-info/METADATA
wagtail_speech-0.2.0.dist-info/WHEEL
wagtail_speech-0.2.0.dist-info/top_level.txt
wagtail_speech-0.2.0.dist-info/RECORD
