Metadata-Version: 2.1
Name: wagtail-speech
Version: 0.2.0
Summary: Turn Wagtail pages into lifelike speech using Amazon Polly.
Author: R.Moorman <rob@vicktor.nl>
Classifier: Environment :: Web Environment
Classifier: Framework :: Django
Classifier: Operating System :: Unix
Classifier: Programming Language :: Python :: 3
Classifier: Framework :: Django
Classifier: Framework :: Wagtail :: 6
Requires-Dist: boto3>=1.4.4
Requires-Dist: django>=1.8
Requires-Dist: wagtail>=1.2
Provides-Extra: test
Requires-Dist: flake8; extra == "test"
Requires-Dist: isort; extra == "test"
Requires-Dist: pytest; extra == "test"
Requires-Dist: pytest-cov; extra == "test"
Requires-Dist: pytest-django; extra == "test"
Requires-Dist: wagtail; extra == "test"
